phenolrs-0.5.12.dist-info/METADATA
phenolrs-0.5.12.dist-info/WHEEL
phenolrs-0.5.12.dist-info/licenses/LICENSE
phenolrs/__init__.py
phenolrs/aql/__init__.py
phenolrs/aql/loader.py
phenolrs/aql/typings.py
phenolrs/networkx/__init__.py
phenolrs/networkx/loader.py
phenolrs/networkx/typings.py
phenolrs/numpy/__init__.py
phenolrs/numpy/loader.py
phenolrs/numpy/typings.py
phenolrs/phenolrs.cpython-311-x86_64-linux-gnu.so
phenolrs/phenolrs.pyi
phenolrs/pyg/__init__.py
phenolrs/pyg/loader.py
phenolrs/pyg/typings.py
phenolrs-0.5.12.dist-info/RECORD
