Metadata-Version: 2.4
Name: phenolrs
Version: 0.5.12
Classifier: Programming Language :: Rust
Classifier: Programming Language :: Python :: Implementation :: CPython
Classifier: Programming Language :: Python :: Implementation :: PyPy
Classifier: Programming Language :: Python :: 3.10
Classifier: Programming Language :: Python :: 3.11
Classifier: Programming Language :: Python :: 3.12
Classifier: Programming Language :: Python :: 3.13
Classifier: Typing :: Typed
Requires-Dist: numpy
Requires-Dist: python-arango>=8.2.6
Requires-Dist: pytest ; extra == 'tests'
Requires-Dist: arango-datasets ; extra == 'tests'
Requires-Dist: adbnx-adapter ; extra == 'tests'
Requires-Dist: torch ; extra == 'torch'
Requires-Dist: torch-geometric ; extra == 'torch'
Requires-Dist: version ; extra == 'dynamic'
Provides-Extra: tests
Provides-Extra: torch
Provides-Extra: dynamic
License-File: LICENSE
Requires-Python: >=3.10
